adndpg/__init__.py
adndpg/_testeur.py
adndpg/clavier.py
adndpg/couleurs.py
adndpg/fenetre.py
adndpg/formes.py
adndpg/images.py
adndpg/sons.py
adndpg/souris.py
adndpg/texte.py
adndpg/fonts/NotoSansSC-Regular.otf
adndpg-0.3.0.dist-info/METADATA
adndpg-0.3.0.dist-info/WHEEL
adndpg-0.3.0.dist-info/licenses/LICENSE
adndpg-0.3.0.dist-info/RECORD
