Metadata-Version: 2.4
Name: adndpg
Version: 0.3.0
Summary: Bibliothèque graphique extrêmement simplifliée en français à des fins éducative, basée sur pyray
Project-URL: Homepage, https://github.com/l-ADN-des-petits-genies/adndpg-python
Project-URL: Documentation, https://github.com/l-ADN-des-petits-genies/adndpg-python#readme
Project-URL: Issues, https://github.com/l-ADN-des-petits-genies/adndpg-python/issues
Author-email: adndpg <contact@adndpg.dev>
License-Expression: MIT
License-File: LICENSE
Keywords: education,french,graphics,raylib
Classifier: Development Status :: 3 - Alpha
Classifier: Intended Audience :: Education
Classifier: License :: OSI Approved :: MIT License
Classifier: Natural Language :: French
Classifier: Programming Language :: Python :: 3
Classifier: Programming Language :: Python :: 3.8
Classifier: Programming Language :: Python :: 3.9
Classifier: Programming Language :: Python :: 3.10
Classifier: Programming Language :: Python :: 3.11
Classifier: Programming Language :: Python :: 3.12
Classifier: Topic :: Education
Classifier: Topic :: Games/Entertainment
Requires-Python: >=3.8
Requires-Dist: raylib>=5.0.0
